<annotation>
	<folder>Labelled Image</folder>
	<filename>011768_Khanif_2.jpg</filename>
	<path>D:\Documents\Project\Smart Thermal System\Android Apps Face Detection\Labelled Image\011768_Khanif_2.jpg</path>
	<source>
		<database>Unknown</database>
	</source>
	<size>
		<width>600</width>
		<height>800</height>
		<depth>3</depth>
	</size>
	<segmented>0</segmented>
	<object>
		<name>Khanif</name>
		<pose>Unspecified</pose>
		<truncated>0</truncated>
		<difficult>0</difficult>
		<bndbox>
			<xmin>138</xmin>
			<ymin>136</ymin>
			<xmax>242</xmax>
			<ymax>267</ymax>
		</bndbox>
	</object>
</annotation>
