<annotation>
	<folder>train</folder>
	<filename>130.jpg</filename>
	<path>D:\Documents\Project\Smart Thermal System\Android Apps Face Detection\TensorFlowColab\object_detection_demo\data\images\train\130.jpg</path>
	<source>
		<database>Unknown</database>
	</source>
	<size>
		<width>600</width>
		<height>800</height>
		<depth>3</depth>
	</size>
	<segmented>0</segmented>
	<object>
		<name>Masker Non-Medic</name>
		<pose>Unspecified</pose>
		<truncated>0</truncated>
		<difficult>0</difficult>
		<bndbox>
			<xmin>203</xmin>
			<ymin>445</ymin>
			<xmax>400</xmax>
			<ymax>601</ymax>
		</bndbox>
	</object>
	<object>
		<name>Arzak</name>
		<pose>Unspecified</pose>
		<truncated>0</truncated>
		<difficult>0</difficult>
		<bndbox>
			<xmin>177</xmin>
			<ymin>292</ymin>
			<xmax>385</xmax>
			<ymax>426</ymax>
		</bndbox>
	</object>
</annotation>
