<annotation>
	<folder>train</folder>
	<filename>Image_109.jpg</filename>
	<path>C:\tensorflow1\models\research\object_detection\images\train\Image_109.jpg</path>
	<source>
		<database>Unknown</database>
	</source>
	<size>
		<width>720</width>
		<height>540</height>
		<depth>3</depth>
	</size>
	<segmented>0</segmented>
	<object>
		<name>botol plastik-Le Minerale</name>
		<pose>Unspecified</pose>
		<truncated>0</truncated>
		<difficult>0</difficult>
		<bndbox>
			<xmin>294</xmin>
			<ymin>41</ymin>
			<xmax>412</xmax>
			<ymax>375</ymax>
		</bndbox>
	</object>
	<object>
		<name>kaleng-Pocari Sweat</name>
		<pose>Unspecified</pose>
		<truncated>0</truncated>
		<difficult>0</difficult>
		<bndbox>
			<xmin>406</xmin>
			<ymin>227</ymin>
			<xmax>503</xmax>
			<ymax>408</ymax>
		</bndbox>
	</object>
</annotation>
