<annotation>
	<folder>LPisau</folder>
	<filename>Pisau_25.jpg</filename>
	<path>E:\Katou desu\FILE SEKOLAH BOI\Mengkoding\Dataset\LPisau\Pisau_25.jpg</path>
	<source>
		<database>Unknown</database>
	</source>
	<size>
		<width>800</width>
		<height>800</height>
		<depth>3</depth>
	</size>
	<segmented>0</segmented>
	<object>
		<name>pisau</name>
		<pose>Unspecified</pose>
		<truncated>1</truncated>
		<difficult>0</difficult>
		<bndbox>
			<xmin>14</xmin>
			<ymin>174</ymin>
			<xmax>800</xmax>
			<ymax>601</ymax>
		</bndbox>
	</object>
</annotation>
